dash_iconify/DashIconify.py
dash_iconify/__init__.py
dash_iconify/_imports_.py
dash_iconify/async-DashIconify.js
dash_iconify/async-DashIconify.js.map
dash_iconify/dash_iconify.min.js
dash_iconify/dash_iconify.min.js.map
dash_iconify/metadata.json
dash_iconify/package-info.json
dash_iconify-0.1.2.dist-info/LICENSE
dash_iconify-0.1.2.dist-info/METADATA
dash_iconify-0.1.2.dist-info/WHEEL
dash_iconify-0.1.2.dist-info/top_level.txt
dash_iconify-0.1.2.dist-info/RECORD
