Metadata-Version: 2.1
Name: dash_iconify
Version: 0.1.2
Summary: Iconify for Plotly Dash
Home-page: https://github.com/snehilvj/dash-iconify
Author: Snehil Vijay <snehilvj@outlook.com>
Author-email: snehilvj@outlook.com
License: MIT
Platform: UNKNOWN
Classifier: Framework :: Dash
